{
    "abbrev": "Kwt.",
    "abbrev_len": "4.00",
    "adm0_a3": "KWT",
    "adm0_a3_is": "KWT",
    "adm0_a3_un": "-99.00",
    "adm0_a3_us": "KWT",
    "adm0_a3_wb": "-99.00",
    "adm0_dif": "0.00",
    "admin": "Kuwait",
    "brk_a3": "KWT",
    "brk_diff": "0.00",
    "brk_group": "",
    "brk_name": "Kuwait",
    "cca2": "KW",
    "cca3": "KWT",
    "ccn3": "414",
    "curencies": [],
    "currencies": [],
    "data_sources": [
        "natural"
    ],
    "economy": "6. Developing region",
    "featurecla": "Admin-0 country",
    "fips_10_": "KU",
    "formal_en": "State of Kuwait",
    "formal_fr": "",
    "gdp_md_est": "301100.00",
    "gdp_year": "2016.00",
    "geo": {
        "borders": [],
        "continent": "Asia",
        "region": "Asia",
        "region_un": "Asia",
        "region_wb": "Middle East & North Africa",
        "subregion": "Western Asia"
    },
    "geou_dif": "0.00",
    "geounit": "Kuwait",
    "gu_a3": "KWT",
    "homepart": "1.00",
    "income_grp": "2. High income: nonOECD",
    "iso_a2": "KW",
    "iso_a3": "KWT",
    "iso_a3_eh": "KWT",
    "iso_n3": "414",
    "labelrank": "6.00",
    "lastcensus": "2010.00",
    "level": "2.00",
    "long_len": "6.00",
    "mapcolor13": "2.00",
    "mapcolor7": "2.00",
    "mapcolor8": "2.00",
    "mapcolor9": "2.00",
    "max_label": "10.00",
    "min_label": "5.00",
    "min_zoom": "0.00",
    "name": {
        "common": "Kuwait",
        "official": "State of Kuwait"
    },
    "name_alt": "",
    "name_ciawf": "Kuwait",
    "name_len": "6.00",
    "name_long": "Kuwait",
    "name_nev": "Kuwait",
    "name_sort": "Kuwait",
    "note_adm0": "",
    "note_brk": "",
    "notes": [
        "Incomplete record due to missing mledoze country."
    ],
    "pop_est": "2875422.00",
    "pop_rank": "12.00",
    "pop_year": "2017.00",
    "postal": "KW",
    "record_type": "country",
    "scalerank": "0",
    "sov_a3": "KWT",
    "sovereignt": "Kuwait",
    "su_a3": "KWT",
    "su_dif": "0.00",
    "subunit": "Kuwait",
    "tiny": "-99.00",
    "type": "Sovereign country",
    "un_a3": "414",
    "wb_a2": "KW",
    "wb_a3": "KWT",
    "wikipedia": "-99.00",
    "woe_id": "23424870.00",
    "woe_id_eh": "23424870.00",
    "woe_note": "Exact WOE match as country"
}